Workbook
Name aporte: Planilha!$C$24
Name aporte: #REF!
Name custo_vida: Planilha!$C$12
Name meses_reserva: Planilha!$C$18
Name meta_reserva: Planilha!$C$20
Name patrimonio: Planilha!$E$10
Name pct_investir: Planilha!$C$14
Name qnt_anos: #REF!
Name qtd_anos: Planilha!$C$25
Name renda_extra: Planilha!$C$10
Name renda_total: Planilha!$C$11
Name rendimento_carteira: Planilha!#REF!
Name rendimento_carteira: #REF!
Name rendimento_liquido: Planilha!$G$16
Name reserva_atual: Planilha!$C$19
Name salario: Planilha!$C$9
Name sobra: Planilha!$C$13
Name sugestao_investimento: Planilha!$C$15
Name taxa_mensal: Planilha!$C$26
Name total_investido: Planilha!$E$16
Name tx_mensal: #REF!

Sheet Planilha
B2: Planejador Financeiro
B5: LEGENDA | C5: Você preenche
C6: Calculado automaticamente
B8: INVESTIMENTO MENSAL | E8: RESULTADO
B9: Salário | C9: 3400 | E9: =IF(qtd_anos<=0,"Preencha o plano para ver o resultado",IF(qtd_anos=1,"Em 1 ano você terá","Em "&qtd_anos&" anos você terá*")) -> Em 10 anos você terá*
B10: Renda extra | C10: 400 | E10: =total_investido+rendimento_liquido -> 230038.69
B11: Renda total | C11: =salario+renda_extra -> 3800
B12: Custo de vida | C12: 2500
B13: Sobra do mês | C13: =renda_total-custo_vida -> 1300
B14: Quanto investir por mês | C14: 0.2
B15: Valor sugerido | C15: =renda_total*pct_investir -> 760 | E15: TOTAL INVESTIDO | G15: RENDIMENTO
E16: =aporte*qtd_anos*12 -> 120000 | G16: =FV(taxa_mensal,qtd_anos*12,-aporte)-total_investido -> 110038.69
B17: RESERVA DE EMERGÊNCIA
B18: Meses de reserva | C18: 6
B19: Reserva atual (Se houver) | C19: 3000
B20: Meta de reserva | C20: =custo_vida*meses_reserva -> 15000 | E20: CENÁRIOS
B21: Restante | C21: =meta_reserva-reserva_atual -> 12000 | E21: Prazo (Anos) | F21: Valor investido | G21: Valor recebido | H21: Renda mensal
E22: 2 | F22: =aporte*E22*12 -> 24000 | G22: =FV(taxa_mensal,E22*12,-aporte) -> 26973.465 | H22: =G22*taxa_mensal -> 269.73465
B23: PLANO DE INVESTIMENTO | E23: 5 | F23: =aporte*E23*12 -> 60000 | G23: =FV(taxa_mensal,E23*12,-aporte) -> 81669.67 | H23: =G23*taxa_mensal -> 816.6967
B24: Investir por mês | C24: 1000 | E24: 10 | F24: =aporte*E24*12 -> 120000 | G24: =FV(taxa_mensal,E24*12,-aporte) -> 230038.69 | H24: =G24*taxa_mensal -> 2300.3869
B25: Por quantos anos | C25: 10 | E25: 20 | F25: =aporte*E25*12 -> 240000 | G25: =FV(taxa_mensal,E25*12,-aporte) -> 989255.37 | H25: =G25*taxa_mensal -> 9892.5537
B26: Rendimento por mês | C26: 0.01 | E26: 30 | F26: =aporte*E26*12 -> 360000 | G26: =FV(taxa_mensal,E26*12,-aporte) -> 3494964.1 | H26: =G26*taxa_mensal -> 34949.641
B28: * Valores brutos, sem considerar o desconto do imposto de renda.

Sheet Perfil 
B2: Perfil de Investidor
B4: Seu Perfil de Investidor | D4: Agressivo
B5: Valor a investir por mês | D5: =Planilha!aporte -> 1000
B7: Tipo de Fundo | C7: Percentual Sugerido | D7: Valor por mês
B8: PAPEL | C8: =VLOOKUP($D$4&"-"&B8,'Base do perfil'!$B$2:$E$20,4,FALSE) -> 0.5 | D8: =C8*$D$5 -> 500
B9: TIJOLO | C9: =VLOOKUP($D$4&"-"&B9,'Base do perfil'!$B$2:$E$20,4,FALSE) -> 0.1 | D9: =C9*$D$5 -> 100
B10: HIBRIDOS | C10: =VLOOKUP($D$4&"-"&B10,'Base do perfil'!$B$2:$E$20,4,FALSE) -> 0.05 | D10: =C10*$D$5 -> 50
B11: FOFs | C11: =VLOOKUP($D$4&"-"&B11,'Base do perfil'!$B$2:$E$20,4,FALSE) -> 0.05 | D11: =C11*$D$5 -> 50
B12: DESENVOLVIMENTO | C12: =VLOOKUP($D$4&"-"&B12,'Base do perfil'!$B$2:$E$20,4,FALSE) -> 0.2 | D12: =C12*$D$5 -> 200
B13: HOTELARIAS | C13: =VLOOKUP($D$4&"-"&B13,'Base do perfil'!$B$2:$E$20,4,FALSE) -> 0.1 | D13: =C13*$D$5 -> 100

Sheet Base do perfil
B2: CHAVE | C2: PERFIL | D2: TIPOS DE FIIs | E2: %
B3: =C3&"-"&D3 -> Conservador-PAPEL | C3: Conservador | D3: PAPEL | E3: 0.3
B4: =C4&"-"&D4 -> Conservador-TIJOLO | C4: Conservador | D4: TIJOLO | E4: 0.5
B5: =C5&"-"&D5 -> Conservador-HIBRIDOS | C5: Conservador | D5: HIBRIDOS | E5: 0.1
B6: =C6&"-"&D6 -> Conservador-FOFs | C6: Conservador | D6: FOFs | E6: 0.1
B7: =C7&"-"&D7 -> Conservador-DESENVOLVIMENTO | C7: Conservador | D7: DESENVOLVIMENTO | E7: 0
B8: =C8&"-"&D8 -> Conservador-HOTELARIAS | C8: Conservador | D8: HOTELARIAS | E8: 0
B9: =C9&"-"&D9 -> Moderado-PAPEL | C9: Moderado | D9: PAPEL | E9: 0.32
B10: =C10&"-"&D10 -> Moderado-TIJOLO | C10: Moderado | D10: TIJOLO | E10: 0.35
B11: =C11&"-"&D11 -> Moderado-HIBRIDOS | C11: Moderado | D11: HIBRIDOS | E11: 0.08
B12: =C12&"-"&D12 -> Moderado-FOFs | C12: Moderado | D12: FOFs | E12: 0.05
B13: =C13&"-"&D13 -> Moderado-DESENVOLVIMENTO | C13: Moderado | D13: DESENVOLVIMENTO | E13: 0.1
B14: =C14&"-"&D14 -> Moderado-HOTELARIAS | C14: Moderado | D14: HOTELARIAS | E14: 0.1
... B20: =C20&"-"&D20 -> Agressivo-HOTELARIAS | C20: Agressivo | D20: HOTELARIAS | E20: 0.1

Sheet Evolução
B2: Evolução do patrimônio
B4: Tabela de apoio do gráfico do Painel. Não precisa editar: ela se atualiza sozinha com os valores digitados na aba Planilha.
B5: Prazo do gráfico (anos) | E5: =MAX(qtd_anos,1) -> 10 | F5: Mínimo de 1 ano.
B6: Prazo do gráfico (meses) | E6: =E5*12 -> 120
B7: Título do gráfico | E7: ="Evolução do patrimônio ao longo de "&E5&IF(E5=1," ano"," anos")&"*" -> Evolução do patrimônio ao longo de 10 anos*
B9: Ponto | C9: Ano | D9: Mês | E9: Total investido | F9: Patrimônio | G9: Rendimento acumulado
B10: 0 | C10: =B10/120*$E$5 -> 0 | D10: =C10*12 -> 0 | E10: =Planilha!aporte*D10 -> 0 | F10: =FV(taxa_mensal,D10,-Planilha!aporte) -> 0 | G10: =F10-E10 -> 0
B11: 1 | C11: =B11/120*$E$5 -> 0.083333333 | D11: =C11*12 -> 1 | E11: =Planilha!aporte*D11 -> 1000 | F11: =FV(taxa_mensal,D11,-Planilha!aporte) -> 1000 | G11: =F11-E11 -> 9.094947e-13
B12: 2 | C12: =B12/120*$E$5 -> 0.16666667 | D12: =C12*12 -> 2 | E12: =Planilha!aporte*D12 -> 2000 | F12: =FV(taxa_mensal,D12,-Planilha!aporte) -> 2010 | G12: =F12-E12 -> 10
B13: 3 | C13: =B13/120*$E$5 -> 0.25 | D13: =C13*12 -> 3 | E13: =Planilha!aporte*D13 -> 3000 | F13: =FV(taxa_mensal,D13,-Planilha!aporte) -> 3030.1 | G13: =F13-E13 -> 30.1
B14: 4 | C14: =B14/120*$E$5 -> 0.33333333 | D14: =C14*12 -> 4 | E14: =Planilha!aporte*D14 -> 4000 | F14: =FV(taxa_mensal,D14,-Planilha!aporte) -> 4060.401 | G14: =F14-E14 -> 60.401
B15: 5 | C15: =B15/120*$E$5 -> 0.41666667 | D15: =C15*12 -> 5 | E15: =Planilha!aporte*D15 -> 5000 | F15: =FV(taxa_mensal,D15,-Planilha!aporte) -> 5101.005 | G15: =F15-E15 -> 101.00501
B16: 6 | C16: =B16/120*$E$5 -> 0.5 | D16: =C16*12 -> 6 | E16: =Planilha!aporte*D16 -> 6000 | F16: =FV(taxa_mensal,D16,-Planilha!aporte) -> 6152.0151 | G16: =F16-E16 -> 152.01506
B17: 7 | C17: =B17/120*$E$5 -> 0.58333333 | D17: =C17*12 -> 7 | E17: =Planilha!aporte*D17 -> 7000 | F17: =FV(taxa_mensal,D17,-Planilha!aporte) -> 7213.5352 | G17: =F17-E17 -> 213.53521
B18: 8 | C18: =B18/120*$E$5 -> 0.66666667 | D18: =C18*12 -> 8 | E18: =Planilha!aporte*D18 -> 8000 | F18: =FV(taxa_mensal,D18,-Planilha!aporte) -> 8285.6706 | G18: =F18-E18 -> 285.67056
B19: 9 | C19: =B19/120*$E$5 -> 0.75 | D19: =C19*12 -> 9 | E19: =Planilha!aporte*D19 -> 9000 | F19: =FV(taxa_mensal,D19,-Planilha!aporte) -> 9368.5273 | G19: =F19-E19 -> 368.52727
B20: 10 | C20: =B20/120*$E$5 -> 0.83333333 | D20: =C20*12 -> 10 | E20: =Planilha!aporte*D20 -> 10000 | F20: =FV(taxa_mensal,D20,-Planilha!aporte) -> 10462.213 | G20: =F20-E20 -> 462.21254
B21: 11 | C21: =B21/120*$E$5 -> 0.91666667 | D21: =C21*12 -> 11 | E21: =Planilha!aporte*D21 -> 11000 | F21: =FV(taxa_mensal,D21,-Planilha!aporte) -> 11566.835 | G21: =F21-E21 -> 566.83467
... B130: 120 | C130: =B130/120*$E$5 -> 10 | D130: =C130*12 -> 120 | E130: =Planilha!aporte*D130 -> 120000 | F130: =FV(taxa_mensal,D130,-Planilha!aporte) -> 230038.69 | G130: =F130-E130 -> 110038.69
